Workbook

Sheet Emitem
A1: CÓDIGO | B1: CORRETORA | C1: E-mail | D1: Supervisor | E1: Data inclusão | F1: EMISSAO DE NF PREVISTA
A2: 153434 | B2: =VLOOKUP(A2,Base!$A:$D,2,0) -> BENVENUTO CORRETORA DE SEGUROS | C2: =VLOOKUP(A2,Base!A:D,3,0) -> financeiro@benvenutoseguros.com.br | D2: =VLOOKUP(B2,Base!B:E,3,0) -> MATHIAS SILVA | F2: Semanal
A3: 111061 | B3: =VLOOKUP(A3,Base!$A:$D,2,0) -> DGA CONSULT E CORRET DE SEG | C3: =VLOOKUP(A3,Base!A:D,3,0) -> daiane@dgacorretoradeseguros.com | D3: =VLOOKUP(B3,Base!B:E,3,0) -> BRUNA SANTANA | F3: Semanal
A4: 51943 | B4: =VLOOKUP(A4,Base!$A:$D,2,0) -> ENOVAX CORRETORA | C4: =VLOOKUP(A4,Base!A:D,3,0) -> diego.sargaco@enovax.com.br | D4: =VLOOKUP(B4,Base!B:E,3,0) -> BEIBIANA MARQUES | F4: Semanal
A5: 82094 | B5: =VLOOKUP(A5,Base!$A:$D,2,0) -> EPOS CORRETORA DE SEGUROS LTDA | C5: =VLOOKUP(A5,Base!A:D,3,0) -> comercial@eposcorretora.com.br | D5: =VLOOKUP(B5,Base!B:E,3,0) -> MATHIAS SILVA | F5: Semanal
A6: 62251 | B6: =VLOOKUP(A6,Base!$A:$D,2,0) -> HALEMBECK CORRETORA DE SEGUROS LTDA | C6: =VLOOKUP(A6,Base!A:D,3,0) -> suportesaude@halembeck.com | D6: =VLOOKUP(B6,Base!B:E,3,0) -> BEIBIANA MARQUES | F6: Semanal
A7: 135917 | B7: =VLOOKUP(A7,Base!$A:$D,2,0) -> ACNWB CORRETORA DE SEGUROS EIRELI | C7: =VLOOKUP(A7,Base!A:D,3,0) -> ACNWBSEGUROS@GMAIL.COM | D7: =VLOOKUP(B7,Base!B:E,3,0) -> MATHIAS SILVA | F7: Mensal
A8: 92371 | B8: =VLOOKUP(A8,Base!$A:$D,2,0) -> KARLA A DE A BASSI EPP | C8: =VLOOKUP(A8,Base!A:D,3,0) -> atendimento@ab6corretora.com.br | D8: =VLOOKUP(B8,Base!B:E,3,0) -> THAYNARA SANTOS | F8: Semanal
A9: 67570 | B9: =VLOOKUP(A9,Base!$A:$D,2,0) -> ADELIZ NUNES | C9: =VLOOKUP(A9,Base!A:D,3,0) -> adeliz.nunes@affinitycorretora.com.br | D9: =VLOOKUP(B9,Base!B:E,3,0) -> ALVARO VARELA | F9: Mensal
A10: 81069 | B10: =VLOOKUP(A10,Base!$A:$D,2,0) -> MOLISANI CONSORCIO E SEGUROS LTDA | C10: =VLOOKUP(A10,Base!A:D,3,0) -> willmolisani@gmail.com | D10: =VLOOKUP(B10,Base!B:E,3,0) -> THAYNARA SANTOS | F10: Semanal
A11: 104779 | B11: =VLOOKUP(A11,Base!$A:$D,2,0) -> ADRIANA CAMPOAMOR CORRET DE SEG LTDA EPP | C11: =VLOOKUP(A11,Base!A:D,3,0) -> adrianac-corretora@uol.com.br | D11: =VLOOKUP(B11,Base!B:E,3,0) -> MICHELE BERNARDO | F11: Mensal
A12: 157518 | B12: =VLOOKUP(A12,Base!$A:$D,2,0) -> PIRANI ADMINISTRADORA E CORRETORA DE SEGUROS LTDA | C12: =VLOOKUP(A12,Base!A:D,3,0) -> beneficios@pirani.com.br | D12: =VLOOKUP(B12,Base!B:E,3,0) -> MATHIAS SILVA | F12: Semanal
A13: 155466 | B13: =VLOOKUP(A13,Base!$A:$D,2,0) -> PLAVEN CORRETORA DE SEGUROS LTDA | C13: =VLOOKUP(A13,Base!A:D,3,0) -> plavencorretora@uol.com.br | D13: =VLOOKUP(B13,Base!B:E,3,0) -> MATHIAS SILVA | F13: Semanal
... A63: 201017 | B63: =VLOOKUP(A63,Base!$A:$D,2,0) -> REDUÇAO SAUDE CONSULTORIA DE BENEFICIOS EIRELI | C63: =VLOOKUP(A63,Base!A:D,3,0) -> fabio@reducaosaude.com.br | D63: =VLOOKUP(B63,Base!B:E,3,0) -> MICHELE BERNARDO | F63: Mensal
A64: 205859 | B64: =VLOOKUP(A64,Base!$A:$D,2,0) -> ERZ ADM e Corretora de Seguros | C64: =VLOOKUP(A64,Base!A:D,3,0) -> consultoria.digital@erzseg.com | D64: =VLOOKUP(B64,Base!B:E,3,0) -> GABRIELLY VARRICHIO | E64: 44939 | F64: Mensal
A65: 205206 | B65: =VLOOKUP(A65,Base!$A:$D,2,0) -> Fontes EF Corretora de Seguros LTDA | C65: =VLOOKUP(A65,Base!A:D,3,0) -> fontes@fontescorretora.com.br | D65: =VLOOKUP(B65,Base!B:E,3,0) -> AMANDA SOUZA | E65: 44900 | F65: Mensal
A66: 202659 | B66: =VLOOKUP(A66,Base!$A:$D,2,0) -> FORMA CORRETORA DE SEGUROS LTDA | C66: =VLOOKUP(A66,Base!A:D,3,0) -> claudia.silva@formaseguros.com.br | D66: =VLOOKUP(B66,Base!B:E,3,0) -> JESSICA GONZAGA | F66: Semanal
A67: 204865 | B67: =VLOOKUP(A67,Base!$A:$D,2,0) -> GABRIEL SOUZA | C67: =VLOOKUP(A67,Base!A:D,3,0) -> gabriel.souza@affinitycorretora.com.br | D67: =VLOOKUP(B67,Base!B:E,3,0) -> ALVARO VARELA | F67: Semanal
A68: 194750 | B68: =VLOOKUP(A68,Base!$A:$D,2,0) -> NBSEGUROS ADMINISTRACAO E CORRETAGEM DE SEGUROS S/S LTDA | C68: =VLOOKUP(A68,Base!A:D,3,0) -> fabia@novabartira.com.br | D68: =VLOOKUP(B68,Base!B:E,3,0) -> THAYNARA SANTOS | F68: Semanal
A69: 97536 | B69: =VLOOKUP(A69,Base!$A:$D,2,0) -> DECIDE CORRETORA DE SEGUROS & CONSULTORIA LTDA | C69: =VLOOKUP(A69,Base!A:D,3,0) -> decideseguros@decideseguros.com.br | D69: =VLOOKUP(B69,Base!B:E,3,0) -> THAYNARA SANTOS | F69: Semanal
A70: 203319 | B70: =VLOOKUP(A70,Base!$A:$D,2,0) -> LUK CONSULTORIA E CORRETORA DE SEGUROS EIRELI | C70: =VLOOKUP(A70,Base!A:D,3,0) -> luciane@lukconsultoria.com.br | D70: =VLOOKUP(B70,Base!B:E,3,0) -> MATHIAS SILVA | F70: Semanal
A71: 66396 | B71: =VLOOKUP(A71,Base!$A:$D,2,0) -> TCA ADMINISTRADORA E CORRETORA DE SEGUROS LTDA | C71: =VLOOKUP(A71,Base!A:D,3,0) -> bruno.beraldo@tcaseguros.com.br | D71: =VLOOKUP(B71,Base!B:E,3,0) -> THALITA MELO | F71: Semanal
A72: 119509 | B72: =VLOOKUP(A72,Base!$A:$D,2,0) -> GABRIELLY VARRICHIO | C72: =VLOOKUP(A72,Base!A:D,3,0) -> gabrielly.varrichio@affinitycorretora.com.br | D72: =VLOOKUP(B72,Base!B:E,3,0) -> ALVARO VARELA | E72: 44930 | F72: Mensal
A73: 89310 | B73: =VLOOKUP(A73,Base!$A:$D,2,0) -> GLOBAL API CORRETORA DE SEGUROS EIRELI | C73: =VLOOKUP(A73,Base!A:D,3,0) -> globalapicorretora@gmail.com | D73: =VLOOKUP(B73,Base!B:E,3,0) -> THAYNARA SANTOS | F73: Mensal
A74: 202636 | B74: =VLOOKUP(A74,Base!$A:$D,2,0) -> IN SOLUCOES EMPRESARIAIS E CORRETAGEM DE SEGUROS LTDA | C74: =VLOOKUP(A74,Base!A:D,3,0) -> operacional@solucoes.in | D74: =VLOOKUP(B74,Base!B:E,3,0) -> AMANDA SOUZA | F74: Semanal
A75: 202849 | B75: =VLOOKUP(A75,Base!$A:$D,2,0) -> SOLUTION FOR LIFE CORRETORA E ADMINISTRADORA DE SEGUROS LTDA | C75: =VLOOKUP(A75,Base!A:D,3,0) -> saude@solutionforlife.com.br | D75: =VLOOKUP(B75,Base!B:E,3,0) -> THALITA MELO | F75: Semanal
A76: 203810 | B76: =VLOOKUP(A76,Base!$A:$D,2,0) -> Via Mais Corretora de Seguros e Beneficios Ltda | C76: =VLOOKUP(A76,Base!A:D,3,0) -> solange.medeiros@viadiretanet.com.br | D76: =VLOOKUP(B76,Base!B:E,3,0) -> MARLI ANDRADE | E76: 44571 | F76: Semanal
A77: 66383 | B77: =VLOOKUP(A77,Base!$A:$D,2,0) -> OPEN HEALTH CORRETORA DE SEGUROS LTDA | C77: =VLOOKUP(A77,Base!A:D,3,0) -> iraja@openseg.com.br | D77: =VLOOKUP(B77,Base!B:E,3,0) -> BRUNA SANTANA | F77: Semanal
A78: 196917 | B78: =VLOOKUP(A78,Base!$A:$D,2,0) -> GOLDEN PROTECTION CORRETORA DE SEGUROS LTDA | C78: =VLOOKUP(A78,Base!A:D,3,0) -> fernandosouza@goldenprotectionseg.com.br | D78: =VLOOKUP(B78,Base!B:E,3,0) -> BEIBIANA MARQUES | F78: Mensal
A79: 183345 | B79: =VLOOKUP(A79,Base!$A:$D,2,0) -> Mappi Corretora de Seguros Ltda Me | C79: =VLOOKUP(A79,Base!A:D,3,0) -> mappiseguros@outlook.com | D79: =VLOOKUP(B79,Base!B:E,3,0) -> THALITA MELO | F79: Semanal
A80: 203729 | B80: =VLOOKUP(A80,Base!$A:$D,2,0) -> SVITEK CORRETORA DE SEGUROS | C80: =VLOOKUP(A80,Base!A:D,3,0) -> svitek@terra.com.br | D80: =VLOOKUP(B80,Base!B:E,3,0) -> THALITA MELO | F80: Semanal
A81: 98574 | B81: =VLOOKUP(A81,Base!$A:$D,2,0) -> FIDELE SEGUROS | C81: =VLOOKUP(A81,Base!A:D,3,0) -> implantacao@fideleseguros.com.br | D81: =VLOOKUP(B81,Base!B:E,3,0) -> GABRIELLY VARRICHIO | F81: Semanal
A82: 202670 | B82: =VLOOKUP(A82,Base!$A:$D,2,0) -> FMP CORRETORA DE SEGUROS LTDA ME | C82: =VLOOKUP(A82,Base!A:D,3,0) -> fabricio@fmpcorretora.com.br | D82: =VLOOKUP(B82,Base!B:E,3,0) -> VINICIUS ADDEU SUP | F82: Semanal
A83: 167960 | B83: =VLOOKUP(A83,Base!$A:$D,2,0) -> MATOS & MONTEIRO CORRETORA DE SEGURO DE VIDA LTDA | C83: =VLOOKUP(A83,Base!A:D,3,0) -> matosmonteiro@matosmonteiro.com.br | D83: =VLOOKUP(B83,Base!B:E,3,0) -> MATHIAS SILVA | F83: Semanal
A84: 203087 | B84: =VLOOKUP(A84,Base!$A:$D,2,0) -> DEBORA PEREIRA DE ANDRADE | C84: =VLOOKUP(A84,Base!A:D,3,0) -> debora@delianseg.com.br | D84: =VLOOKUP(B84,Base!B:E,3,0) -> BRUNA SANTANA | E84: 44609 | F84: Semanal
A85: 77966 | B85: =VLOOKUP(A85,Base!$A:$D,2,0) -> MORETO E GOUVEA CORRETORA DE SEGUROS LTDA -EPP | C85: =VLOOKUP(A85,Base!A:D,3,0) -> nathalia@moretoegouvea.com.br | D85: =VLOOKUP(B85,Base!B:E,3,0) -> THAYNARA SANTOS | E85: 44638 | F85: Semanal
A86: 202360 | B86: =VLOOKUP(A86,Base!$A:$D,2,0) -> BAUER CORRETORA DE SEGUROS LTDA | C86: =VLOOKUP(A86,Base!A:D,3,0) -> comercial@bauercorretora.com | D86: =VLOOKUP(B86,Base!B:E,3,0) -> MYLLENA FERNANDES | E86: 44648 | F86: Semanal
A87: 164878 | B87: =VLOOKUP(A87,Base!$A:$D,2,0) -> M. K. BRASIL ADMINISTRACAO E CORRETAGEM DE SEGUROS LTDA | C87: =VLOOKUP(A87,Base!A:D,3,0) -> COMERCIALSAUDE@MKBRASIL.COM | D87: =VLOOKUP(B87,Base!B:E,3,0) -> MATHIAS SILVA | E87: 44655 | F87: Semanal
A88: 190606 | B88: =VLOOKUP(A88,Base!$A:$D,2,0) -> KENDRA Corretora de Seguros Ltda | C88: =VLOOKUP(A88,Base!A:D,3,0) -> tatiana@kendraseguros.com.br | D88: =VLOOKUP(B88,Base!B:E,3,0) -> THALITA MELO | F88: Semanal
A89: 204013 | B89: =VLOOKUP(A89,Base!$A:$D,2,0) -> VIVER SEGURO - CONSULTORIA, ADMINISTRAÇÃO E CORRETAGEM DE SEGUROS | C89: =VLOOKUP(A89,Base!A:D,3,0) -> rubens@viversegurocorretora.com.br | D89: =VLOOKUP(B89,Base!B:E,3,0) -> BRUNA SANTANA | E89: 44662 | F89: Semanal
A90: 153418 | B90: =VLOOKUP(A90,Base!$A:$D,2,0) -> ILHA CORRETORA DE SEGUROS LTDA. | C90: =VLOOKUP(A90,Base!A:D,3,0) -> daniela@ilhacorretora.com.br | D90: =VLOOKUP(B90,Base!B:E,3,0) -> MATHIAS SILVA | F90: Mensal
A91: 162803 | B91: =VLOOKUP(A91,Base!$A:$D,2,0) -> Orbi Corretora e Administradora de Seguros Ltda | C91: =VLOOKUP(A91,Base!A:D,3,0) -> Ricardo@orbiseguros.com.br | D91: =VLOOKUP(B91,Base!B:E,3,0) -> MATHIAS SILVA | E91: 44679 | F91: Semanal
A92: 203570 | B92: =VLOOKUP(A92,Base!$A:$D,2,0) -> JACQUELINE BARBOZA | C92: =VLOOKUP(A92,Base!A:D,3,0) -> jacqueline.barboza@affinitycorretora.com.br | D92: =VLOOKUP(B92,Base!B:E,3,0) -> ALVARO VARELA | F92: Mensal
A93: 202727 | B93: =VLOOKUP(A93,Base!$A:$D,2,0) -> BDV CONSULTORIA E CORRETAGEM DE SEGUROS LTDA | C93: =VLOOKUP(A93,Base!A:D,3,0) -> almir@bdvconsultoria.com.br | D93: =VLOOKUP(B93,Base!B:E,3,0) -> MATHIAS SILVA | E93: 44683 | F93: Semanal
A94: 157505 | B94: =VLOOKUP(A94,Base!$A:$D,2,0) -> REVISA SOLUCOES EM GESTAO DE BENEFICIOS LTDA | C94: =VLOOKUP(A94,Base!A:D,3,0) -> Juliano@revisacorretora.com.br | D94: =VLOOKUP(B94,Base!B:E,3,0) -> PAMELA LIMA | E94: 44697 | F94: Semanal
A95: 202173 | B95: =VLOOKUP(A95,Base!$A:$D,2,0) -> HEALTH & CARE CORRETORA DE SEGUROS LTDA | C95: =VLOOKUP(A95,Base!A:D,3,0) -> fabianne@corretorahec.com.br | D95: =VLOOKUP(B95,Base!B:E,3,0) -> BEIBIANA MARQUES | E95: 44712 | F95: Semanal
A96: 204064 | B96: =VLOOKUP(A96,Base!$A:$D,2,0) -> Guerato Corretora de Seguros LTDA | C96: =VLOOKUP(A96,Base!A:D,3,0) -> contato@gueratoseguros.com.br | D96: =VLOOKUP(B96,Base!B:E,3,0) -> BEIBIANA MARQUES | E96: 44714 | F96: Semanal
A97: 204529 | B97: =VLOOKUP(A97,Base!$A:$D,2,0) -> R.B. BOTTA CORRETORA DE SEGUROS LTDA | C97: =VLOOKUP(A97,Base!A:D,3,0) -> robottaseguros@gmail.com | D97: =VLOOKUP(B97,Base!B:E,3,0) -> MATHIAS SILVA | F97: Semanal
A98: 67589 | B98: =VLOOKUP(A98,Base!$A:$D,2,0) -> R & R RODRIGUES & ROCHA CORRETORA DE SEGUROS LTDA | C98: =VLOOKUP(A98,Base!A:D,3,0) -> renata@rodrigueserocha.com.br | D98: =VLOOKUP(B98,Base!B:E,3,0) -> BEIBIANA MARQUES | F98: Semanal
A99: 204029 | B99: =VLOOKUP(A99,Base!$A:$D,2,0) -> TEXAS AFFINITY CORRETORA DE SEGUROS LTDA | C99: =VLOOKUP(A99,Base!A:D,3,0) -> comercial@texasseguros.com.br | D99: =VLOOKUP(B99,Base!B:E,3,0) -> ALVARO VARELA | F99: Semanal
A100: 204821 | B100: =VLOOKUP(A100,Base!$A:$D,2,0) -> AVALANCHE DE VENDAS UNIPESSOAL LTDA | C100: =VLOOKUP(A100,Base!A:D,3,0) -> affinity@williamcruz.net | D100: =VLOOKUP(B100,Base!B:E,3,0) -> MATHIAS SILVA | F100: Semanal
A101: 204158 | B101: =VLOOKUP(A101,Base!$A:$D,2,0) -> Fiorano Corretora de Seguros Ltda | C101: =VLOOKUP(A101,Base!A:D,3,0) -> fabio.gasparro@fioranoseguros.com.br | D101: =VLOOKUP(B101,Base!B:E,3,0) -> AMANDA SOUZA | F101: Semanal
A102: 204315 | B102: =VLOOKUP(A102,Base!$A:$D,2,0) -> ALVESP HOME CORRETORA DE SEGUROS LTDA | C102: =VLOOKUP(A102,Base!A:D,3,0) -> marcel.alves@aehcorretora.com.br | D102: =VLOOKUP(B102,Base!B:E,3,0) -> BEIBIANA MARQUES | F102: Semanal
A103: 204191 | B103: =VLOOKUP(A103,Base!$A:$D,2,0) -> TELMA DOS SANTOS MARTINS CORRETAGEM E CONSULTORIA EM SEGUROS LTDA | C103: =VLOOKUP(A103,Base!A:D,3,0) -> telmamartins8230@gmail.com | D103: =VLOOKUP(B103,Base!B:E,3,0) -> THAYNARA SANTOS | F103: Semanal
A104: 157533 | B104: =VLOOKUP(A104,Base!$A:$D,2,0) -> SULLA VITA CONSULTORIA E CORRETORA DE SEGUROS S/S LTDA | C104: =VLOOKUP(A104,Base!A:D,3,0) -> fabiomundel@sullavita.com.br | D104: =VLOOKUP(B104,Base!B:E,3,0) -> MATHIAS SILVA | F104: Semanal
A105: 115445 | B105: =VLOOKUP(A105,Base!$A:$D,2,0) -> CAMILA VIEIRA DA SILVA | C105: =VLOOKUP(A105,Base!A:D,3,0) | D105: =VLOOKUP(B105,Base!B:E,3,0) -> THAYNARA SANTOS | F105: Semanal
A106: 66399 | B106: =VLOOKUP(A106,Base!$A:$D,2,0) -> K&W CORRETORA DE SEGUROS LTDA | C106: =VLOOKUP(A106,Base!A:D,3,0) -> kew@kewcorretoradeseguros.com.br | D106: =VLOOKUP(B106,Base!B:E,3,0) -> BEIBIANA MARQUES | F106: Semanal
A107: 204914 | B107: =VLOOKUP(A107,Base!$A:$D,2,0) -> Vida360 CORRETORA DE SEGUROS LTDA | C107: =VLOOKUP(A107,Base!A:D,3,0) -> seguros@vida360corretora.com.br | D107: =VLOOKUP(B107,Base!B:E,3,0) -> MARLI ANDRADE | F107: Semanal
A108: 205381 | B108: =VLOOKUP(A108,Base!$A:$D,2,0) -> LARISSA DA SILVA TEIXEIRA | C108: =VLOOKUP(A108,Base!A:D,3,0) -> larissa.teixeira@completoseguros.com.br | D108: =VLOOKUP(B108,Base!B:E,3,0) -> VINICIUS ADDEU SUP | F108: Semanal
... A146: 82093 | B146: =VLOOKUP(A146,Base!$A:$D,2,0) -> GORGATE & OLIVEIRA CORRETORA DE SEGUROS LTDA | C146: =VLOOKUP(A146,Base!A:D,3,0) -> adriana@gorgate.com.br | D146: =VLOOKUP(B146,Base!B:E,3,0) -> BEIBIANA MARQUES | F146: Semanal
A147: 205505 | B147: =VLOOKUP(A147,Base!$A:$D,2,0) -> JENNIFER OLIVEIRA | C147: =VLOOKUP(A147,Base!A:D,3,0) -> jennifer.oliveira@affinitycorretora.com.br | D147: =VLOOKUP(B147,Base!B:E,3,0) -> ALVARO VARELA | E147: 44930 | F147: Semanal
A148: 86231 | B148: =VLOOKUP(A148,Base!$A:$D,2,0) -> PRIME SECURE CORRETORA | C148: =VLOOKUP(A148,Base!A:D,3,0) -> rmilharezi@primesecure.com.br | D148: =VLOOKUP(B148,Base!B:E,3,0) -> GABRIELLY VARRICHIO | F148: Mensal
A149: 204525 | B149: =VLOOKUP(A149,Base!$A:$D,2,0) -> RODOSEG CORRETORA DE SEGUROS E CONSULTORIA LTDA | C149: =VLOOKUP(A149,Base!A:D,3,0) -> rodoseg@rodosegseguros.com.br | D149: =VLOOKUP(B149,Base!B:E,3,0) -> AMANDA PUZISKI | F149: Semanal
A150: 204959 | B150: =VLOOKUP(A150,Base!$A:$D,2,0) -> AG SEGUROS GIANINI CORRETORA LTDA | C150: =VLOOKUP(A150,Base!A:D,3,0) -> sandra.gianini@agseguros.com.br | D150: =VLOOKUP(B150,Base!B:E,3,0) -> THALITA MELO | F150: Semanal
A151: 106931 | B151: =VLOOKUP(A151,Base!$A:$D,2,0) -> JESSICA GONZAGA | C151: =VLOOKUP(A151,Base!A:D,3,0) -> jessica.gonzaga@affinitycorretora.com.br | D151: =VLOOKUP(B151,Base!B:E,3,0) -> ALVARO VARELA | F151: Semanal
A152: 202349 | B152: =VLOOKUP(A152,Base!$A:$D,2,0) -> C10 CORRETORA DE SEGUROS LTDA | C152: =VLOOKUP(A152,Base!A:D,3,0) -> alex@c10corretora.com.br | D152: =VLOOKUP(B152,Base!B:E,3,0) -> JESSICA GONZAGA | F152: Semanal
A153: 205498 | B153: =VLOOKUP(A153,Base!$A:$D,2,0) -> Larissa dos Santos Torres | C153: =VLOOKUP(A153,Base!A:D,3,0) -> larissaldstorres@gmail.com | D153: =VLOOKUP(B153,Base!B:E,3,0) -> VINICIUS ADDEU SUP | F153: Semanal
A154: 51902 | B154: =VLOOKUP(A154,Base!$A:$D,2,0) -> KMP CORRETORA | C154: =VLOOKUP(A154,Base!A:D,3,0) -> kmp@kmpcorretora.com.br | D154: =VLOOKUP(B154,Base!B:E,3,0) -> BEIBIANA MARQUES | F154: Mensal
A155: 88282 | B155: =VLOOKUP(A155,Base!$A:$D,2,0) -> LASTRO CORRETORA DE SEGUROS EIRELI | C155: =VLOOKUP(A155,Base!A:D,3,0) -> acseguros@lastrobrokers.com.br | D155: =VLOOKUP(B155,Base!B:E,3,0) -> THAYNARA SANTOS | F155: Mensal
A156: 204512 | B156: =VLOOKUP(A156,Base!$A:$D,2,0) -> PATRIOTA CORRETORA DE SEGUROS EIRELI | C156: =VLOOKUP(A156,Base!A:D,3,0) -> financeiro@ruizseguros.com.br | D156: =VLOOKUP(B156,Base!B:E,3,0) -> THALITA MELO | F156: Semanal
A157: 204147 | B157: =VLOOKUP(A157,Base!$A:$D,2,0) -> MPIMENTEL ADMINISTRADORA E CORRETORA DE SEGUROS LTDA | C157: =VLOOKUP(A157,Base!A:D,3,0) -> pimentelzap@uol.com.br | D157: =VLOOKUP(B157,Base!B:E,3,0) -> BEIBIANA MARQUES | F157: Semanal
A158: 205719 | B158: =VLOOKUP(A158,Base!$A:$D,2,0) -> Evellin Santos Soares Guilherme | C158: =VLOOKUP(A158,Base!A:D,3,0) -> eve.santtos0@gmail.com | D158: =VLOOKUP(B158,Base!B:E,3,0) -> VINICIUS ADDEU SUP | F158: Semanal
A159: 205101 | B159: =VLOOKUP(A159,Base!$A:$D,2,0) -> W MARTINS CORRETORA DE SEGUROS EIRELI | C159: =VLOOKUP(A159,Base!A:D,3,0) -> gerencia@wmartinsseguros.com.br | D159: =VLOOKUP(B159,Base!B:E,3,0) -> THAYNARA SANTOS | F159: Semanal
A160: 205483 | B160: =VLOOKUP(A160,Base!$A:$D,2,0) -> FRANCISCA CLEMENTINO DE SOUSA | C160: =VLOOKUP(A160,Base!A:D,3,0) -> nfe@bugconsultoria.com.br | D160: =VLOOKUP(B160,Base!B:E,3,0) -> GABRIELLY VARRICHIO | F160: Semanal
A161: 205637 | B161: =VLOOKUP(A161,Base!$A:$D,2,0) -> JEFFERSON DOS SANTOS | C161: =VLOOKUP(A161,Base!A:D,3,0) -> consultor18@corretoraffinity.com.br | D161: =VLOOKUP(B161,Base!B:E,3,0) -> VINICIUS ADDEU SUP | E161: 44869 | F161: Semanal
A162: 205753 | B162: =VLOOKUP(A162,Base!$A:$D,2,0) -> BRENDA MARIA ALVES DE MOURA | C162: =VLOOKUP(A162,Base!A:D,3,0) -> brenda.alves@completoseguros.com.br | D162: =VLOOKUP(B162,Base!B:E,3,0) -> VINICIUS ADDEU SUP | E162: 44869 | F162: Semanal
A163: 125759 | B163: =VLOOKUP(A163,Base!$A:$D,2,0) -> CURATRIX CORRETORA DE SEGUROS EIRELI | C163: =VLOOKUP(A163,Base!A:D,3,0) -> curatrixcorretora@gmail.com | D163: =VLOOKUP(B163,Base!B:E,3,0) -> THAYNARA SANTOS | E163: 44875 | F163: Semanal
A164: 205632 | B164: =VLOOKUP(A164,Base!$A:$D,2,0) -> Luiz Mateus Lopes De Siqueira | C164: =VLOOKUP(A164,Base!A:D,3,0) -> teuz9625@gmail.com | D164: =VLOOKUP(B164,Base!B:E,3,0) -> THAYNARA SANTOS | E164: 44876 | F164: Semanal
A165: 204645 | B165: =VLOOKUP(A165,Base!$A:$D,2,0) -> A. DA SILVA FERREIRA LIMITADA | C165: =VLOOKUP(A165,Base!A:D,3,0) | D165: =VLOOKUP(B165,Base!B:E,3,0) -> JESSICA GONZAGA | E165: 44876 | F165: Semanal
A166: 205679 | B166: =VLOOKUP(A166,Base!$A:$D,2,0) -> Cinthia Regina Barbosa | C166: =VLOOKUP(A166,Base!A:D,3,0) -> cinthia.barbosa995@gmail.com | D166: =VLOOKUP(B166,Base!B:E,3,0) -> VINICIUS ADDEU SUP | E166: 44876 | F166: Semanal
A167: 204934 | B167: =VLOOKUP(A167,Base!$A:$D,2,0) -> MONTE LIFE CONSULTORIA E CORRETORA DE SEGUROS LTDA | C167: =VLOOKUP(A167,Base!A:D,3,0) | D167: =VLOOKUP(B167,Base!B:E,3,0) -> AMANDA PUZISKI | E167: 44881 | F167: Semanal
A168: 62238 | B168: =VLOOKUP(A168,Base!$A:$D,2,0) -> ADRIANA CIARINI | C168: =VLOOKUP(A168,Base!A:D,3,0) -> adriana.ciarini@affinitycorretora.com | D168: =VLOOKUP(B168,Base!B:E,3,0) -> ALVARO VARELA | F168: Semanal
A169: 205466 | B169: =VLOOKUP(A169,Base!$A:$D,2,0) -> LIDIANE DA ROCHA ABREU | C169: =VLOOKUP(A169,Base!A:D,3,0) -> lidiane.rocha@affinitycorretora.com.br | D169: =VLOOKUP(B169,Base!B:E,3,0) -> ALVARO VARELA | F169: Semanal
A170: 203445 | B170: =VLOOKUP(A170,Base!$A:$D,2,0) -> LUCIMEIRE DE CAMARGO SEABRA | C170: =VLOOKUP(A170,Base!A:D,3,0) -> meirecamargo.saude@yahoo.com | D170: =VLOOKUP(B170,Base!B:E,3,0) -> JESSICA GONZAGA | F170: Mensal
A171: 51833 | B171: =VLOOKUP(A171,Base!$A:$D,2,0) -> MAIN LAND 3 ADMINISTRADORA E CORRETORA DE SEGUROS H. LTDA EPP | C171: =VLOOKUP(A171,Base!A:D,3,0) -> mainland@mainland.com.br | D171: =VLOOKUP(B171,Base!B:E,3,0) -> THALITA MELO | E171: 44680 | F171: Mensal
A172: 136940 | B172: =VLOOKUP(A172,Base!$A:$D,2,0) -> MARLI ANDRADE | C172: =VLOOKUP(A172,Base!A:D,3,0) -> marli.andrade@affinitycorretora.com.br | D172: =VLOOKUP(B172,Base!B:E,3,0) -> MARLI ANDRADE | F172: Mensal
A173: 200185 | B173: =VLOOKUP(A173,Base!$A:$D,2,0) -> MARLI. ANDRADE | C173: =VLOOKUP(A173,Base!A:D,3,0) -> marli@affinitycorretora.com.br | D173: =VLOOKUP(B173,Base!B:E,3,0) -> MARLI ANDRADE | F173: Mensal
A174: 76912 | B174: =VLOOKUP(A174,Base!$A:$D,2,0) -> MAROEZ CORRETORA DE SEGUROS LTDA ME | C174: =VLOOKUP(A174,Base!A:D,3,0) -> marcio@maroez.com.br | D174: =VLOOKUP(B174,Base!B:E,3,0) -> THAYNARA SANTOS | F174: Mensal
A175: 114182 | B175: =VLOOKUP(A175,Base!$A:$D,2,0) -> MATHEUS LIMA BOCUTTE | C175: =VLOOKUP(A175,Base!A:D,3,0) -> Matheus.bocutte@gmail.com | D175: =VLOOKUP(B175,Base!B:E,3,0) -> VINICIUS ADDEU SUP | F175: Mensal
A176: 200481 | B176: =VLOOKUP(A176,Base!$A:$D,2,0) -> MATHIAS SILVA | C176: =VLOOKUP(A176,Base!A:D,3,0) -> mathias.silva@affinitycorretora.com.br | D176: =VLOOKUP(B176,Base!B:E,3,0) -> ALVARO VARELA | F176: Mensal
A177: 104816 | B177: =VLOOKUP(A177,Base!$A:$D,2,0) -> MF&D CORRETORA DE SEG LTDA | C177: =VLOOKUP(A177,Base!A:D,3,0) -> mariafernanda@mfmais.com.br | D177: =VLOOKUP(B177,Base!B:E,3,0) -> THAYNARA SANTOS | F177: Semanal
A178: 65341 | B178: =VLOOKUP(A178,Base!$A:$D,2,0) -> MICHELE BERNARDO | C178: =VLOOKUP(A178,Base!A:D,3,0) -> michele.bernardo@affinitycorretora.com.br | D178: =VLOOKUP(B178,Base!B:E,3,0) -> ALVARO VARELA | F178: Mensal
A179: 75833 | B179: =VLOOKUP(A179,Base!$A:$D,2,0) -> MONICA PEREIRA | C179: =VLOOKUP(A179,Base!A:D,3,0) -> monica.pereira@affinitycorretora.com | D179: =VLOOKUP(B179,Base!B:E,3,0) -> ALVARO VARELA | F179: Semanal
A180: 115434 | B180: =VLOOKUP(A180,Base!$A:$D,2,0) -> MOVE CONSULTORIA E CORRETORA DE SEGUROS | C180: =VLOOKUP(A180,Base!A:D,3,0) -> contato@movecorretora.com.br | D180: =VLOOKUP(B180,Base!B:E,3,0) -> AMANDA SOUZA | F180: Semanal
A181: 202903 | B181: =VLOOKUP(A181,Base!$A:$D,2,0) -> MPM SECURITY CORRETORA DE SEGUROS LTDA | C181: =VLOOKUP(A181,Base!A:D,3,0) -> adm@mpmcorretora.com.br | D181: =VLOOKUP(B181,Base!B:E,3,0) -> BRUNA SANTANA | E181: 44895 | F181: Mensal
A182: 145099 | B182: =VLOOKUP(A182,Base!$A:$D,2,0) -> NATIONAL CORRETORA DE SEGUROS LTDA | C182: =VLOOKUP(A182,Base!A:D,3,0) | D182: =VLOOKUP(B182,Base!B:E,3,0) -> MATHIAS SILVA | F182: Mensal
A183: 204812 | B183: =VLOOKUP(A183,Base!$A:$D,2,0) -> ONIX NOVA CORRETORA DE SEGUROS LTDA | C183: =VLOOKUP(A183,Base!A:D,3,0) -> felipe@onixseguros.com.br | D183: =VLOOKUP(B183,Base!B:E,3,0) -> THAYNARA SANTOS | E183: 44929 | F183: Mensal
A184: 146120 | B184: =VLOOKUP(A184,Base!$A:$D,2,0) -> PETERSON MASCARENHAS | C184: =VLOOKUP(A184,Base!A:D,3,0) -> corretorespeterson@affinitycorrtora.com.br | D184: =VLOOKUP(B184,Base!B:E,3,0) -> ALVARO VARELA | F184: Mensal
A185: 170024 | B185: =VLOOKUP(A185,Base!$A:$D,2,0) -> PETERSON MASCARENHAS - Spread | C185: =VLOOKUP(A185,Base!A:D,3,0) -> peterson.mascarenhas@affinitycorretora.com.br | D185: =VLOOKUP(B185,Base!B:E,3,0) -> ALVARO VARELA | F185: Mensal
A186: 51204 | B186: =VLOOKUP(A186,Base!$A:$D,2,0) -> PHILIPE GOMES | C186: =VLOOKUP(A186,Base!A:D,3,0) -> philipe.gomes@spcareseguros.com.br | D186: =VLOOKUP(B186,Base!B:E,3,0) -> ALVARO VARELA | F186: Mensal
...

Sheet Base
A1: Código | B1: Nome | C1: Email | D1: Assistente
A2: 215876 | B2: ANDREA PAULA BARRETO NEJAIM MEIRA | C2: corretoraandreameira@gmail.com | D2: JAQUELINE SOARES
A3: 216906 | B3: IMPACTO CERTIFICAÇÕES E CORRETORA DE SEGUROS LTDA | C3: seguros2@impactoassessores.com.br | D3: JESSICA GONZAGA
A4: 208641 | B4: 11PONTO11 CORRETORA DE SEGUROS & PROTECAO LTDA | C4: saulo.guimaraes@11ponto11.com.br | D4: THALITA MELO
A5: 212605 | B5: 19.865.635 ELAINE CRISTINA DE OLIVEIRA COSTA SABINO | C5: prayersaudeconsultoria@gmail.com | D5: JACQUELINE BARBOZA
A6: 217041 | B6: 2 EM 1 CONSULTORIA EM BENEFICIOS | C6: 2em1consultoriarj@gmail.com | D6: CAROLINE VIVAS
A7: 211463 | B7: 22.281.415 MIRIAM DE PAULA DA SILVA | C7: miriamtedhels@gmail.com | D7: MICHELE OLIVEIRA
A8: 217247 | B8: 26.409.715 CAMILA VIEIRA DA SILVA | C8: camila.vieira@adhikariconsultoria.com.br | D8: THAYNARA SANTOS
A9: 214207 | B9: 26.983.424 VANESSA DE CASTRO GALEGO DIAS | C9: vanessa@galegosaude.com.br | D9: INGRID SOUZA
A10: 206281 | B10: 2R'S CORRETORA E ADM DE SEGUROS LTDA | C10: rita@2rsseguros.com.br | D10: THAYNARA SANTOS
A11: 216680 | B11: 30.607.650 FLAVIO VENTURA DE ANDRADE | C11: flaviooventura@gmail.com | D11: NATHALIA NARDELLI
A12: 207270 | B12: 33.720.035 VICTORIA ALVES GREGORIO MARQUES | C12: g.vsaopaulo@outlook.com | D12: THALITA MELO
A13: 201046 | B13: 34.980.893 RENATA MORAES NEVES RODRIGUES | C13: renata.nrodrigues@hotmail.com | D13: AMANDA SOUZA
... A22: 211535 | B22: 42.930.215 ANA PAULA BUSCHERMOHLE | C22: anabplanosdesaude@outlook.com | D22: CAROLINE VIVAS
A23: 211509 | B23: 43.199.169 PRISCYLA DE ANDRADE FERREIRA | D23: LAIS LIMA
A24: 217201 | B24: 43.956.997 RAPHAEL TAVARES DA SILVA MANHAES | C24: raphael.ts.manhaes@gmail.com | D24: NATHALIA NARDELLI
A25: 216866 | B25: 44.642.472 ALEXANDRE CHERFAN GOULART NOGUEIRA | C25: 1986.acgn@gmail.com | D25: DANIELA BARBOSA
A26: 214777 | B26: 45.714.980 ADRIANA SAMPAIO CUNHA DA COSTA | C26: adrianasampaiocorretora@gmail.com | D26: ANNA FREITAS
A27: 212463 | B27: 47.717.458 ALINE MARIA DO NASCIMENTO | C27: aline_amn@yahoo.com.br | D27: NATHALIA NARDELLI
A28: 206513 | B28: 49.162.551 YAN ZANELATO DA SILVA | C28: wayconsig@gmail.com | D28: NATHALIA NARDELLI
A29: 214254 | B29: 49.396.915 JOAO PAULO REATTI | C29: joaopauloreatti@gmail.com | D29: INGRID SOUZA
A30: 211575 | B30: 49.412.381 Tamara Ingrid dos Santos | C30: seguros.tamaraingrid@gmail.com | D30: JENNIFER OLIVEIRA
A31: 215798 | B31: 49.466.127 BRUNO ROBERTO DE LIMA BENTO | C31: bl.corretorr@gmail.com | D31: ANNA FREITAS
A32: 215013 | B32: 49337555 GABRIELA FRANZIN JULIAO DA SILVA | C32: gabrielafranzinjs@gmail.com | D32: MARLI ANDRADE
A33: 210837 | B33: 4HELP CORRETORA DE SEGUROS LTDA | C33: andre@4helpseguros.com.br | D33: BRUNA SANTANA
A34: 208616 | B34: 4YOU CORRETORA DE SEGUROS LTDA | C34: analu@4youcorretoradeseguros.com.br | D34: THALITA MELO
A35: 213478 | B35: 50.610.554 LUCAS NUNES ALVES | C35: lucasnunes@azakseguros.com.br | D35: THALITA MELO
... A37: 214979 | B37: 51.200.170 GABRIELA SAMPAIO CASTRO | C37: scastro.gabriela@gmail.com | D37: GABRIELLY VARRICHIO
A38: 211379 | B38: 51.468.632 MARIA EDUARDA DOS SANTOS MACHADO | D38: ANNA FREITAS
A39: 216941 | B39: 51.641.287 TAINA DA SILVA LIMA | C39: taina.lima@rzplanos.com.br | D39: MICHELE BERNARDO
A40: 215503 | B40: 52.665.074 ANDRESSA MORALES BATISTA ROCHA | C40: dessamnb@gmail.com | D40: JESSICA GONZAGA
A41: 216431 | B41: 53.335.627 ROSIANE CORDEIRO FARIAS | C41: rosiane.saude@hotmail.com | D41: DANIELA BARBOSA
A42: 216463 | B42: 53.626.759 MATHEUS MENDES MORAES | C42: sdrmatheusmendes@gmail.com | D42: INGRID SOUZA
A43: 111042 | B43: 53.992.708 ANDERSON JANDOSA CORDEIRO | C43: ajandosa.consultor@gmail.com | D43: JESSICA GONZAGA
A44: 214100 | B44: 55.064.723 ALEXANDRE JULIO CEDIRIAN | C44: acedirian@gmail.com | D44: MICHELE BERNARDO
A45: 214387 | B45: 55.071.073 RAFAEL OLIVEIRA DOS SANTOS GONÇALVES | C45: aaseguros.corretora@gmail.com | D45: MARLI ANDRADE
A46: 214085 | B46: 55.195.486 LUCAS NOBREGA DE OLIVEIRA | C46: nobregalucas911@gmail.com | D46: FLAVIO TEODORO
A47: 217235 | B47: 55.304.469 CLARICE ALVES SOUZA | C47: clarice.corretoradeseguros@gmail.com | D47: AMANDA PUZISKI
A48: 215765 | B48: 56.201.853 RAPHAEL ZIBINI LAMUCIO | C48: raphael@zibiniseguros.com.br | D48: GABRIELLY VARRICHIO
A49: 214982 | B49: 56.823.426 FRANCISCO MOINO FILHO | C49: redire19@gmail.com | D49: JESSICA GONZAGA
A50: 214167 | B50: 58.259.248 CRISTINA MARQUES SILVA CASSIANO | C50: connectar.mais@gmail.com | D50: CAROLINE VIVAS
... A52: 211522 | B52: 58.808.560 DAYANE ALESSANDRA SILVA MONTEIRO | C52: dayane.segurosaude@outlook.com | D52: GABRIELLY VARRICHIO
A53: 211821 | B53: 59.111.274 SAMIRA RODRIGUES SANTOS | D53: VINICIUS ADDEU SUP
A54: 216439 | B54: 59.221.013 FABIO ALEXANDRE GONCALVES | C54: fabio.consorcioeinvestimentos@gmail.com | D54: JULIA RIBEIRO
A55: 216522 | B55: 59.687.976 ERIKA ROCHA SANTOS | C55: erconsultoriaemsaude@gmail.com | D55: MATHIAS SILVA
A56: 212240 | B56: 59814486 VITORIA LIMA CARDOSO DE BRITO | C56: amplitudecorretora@gmail.com | D56: JESSICA GONZAGA
A57: 215051 | B57: 60.828.312 GERUZA GOMES DOS SANTOS | C57: caahlima98@gmail.com | D57: DANIELA BARBOSA
A58: 213666 | B58: 61.719.775 ANA PAULA LUQUE DE ABREU | C58: aluquedeabreu@gmail.com | D58: MARLI ANDRADE
A59: 215245 | B59: 61.720.988 CASSIO BARRETO AMARO DE OLIVEIRA | C59: cassio.oliveira@completoseguros.com.br | D59: VINICIUS ADDEU SUP
A60: 213929 | B60: 62.089.007 MOISES MARINHO ALVES | C60: grupomarinho38@gmail.com | D60: CAROLINE VIVAS
A61: 213970 | B61: 62.119.642 FERNANDO DE PAULA RODRIGUES | D61: MICHELE BERNARDO
A62: 215106 | B62: 62.137.206 LUCIVO MANOEL DA SILVA | C62: lucivocorretor@gmail.com | D62: JULIA RIBEIRO
A63: 215942 | B63: 64.860.209 JEFERSON FERREIRA DOS SANTOS JUNIOR | C63: papel_21@hotmail.com | D63: DANIELA BARBOSA
A64: 217101 | B64: 65.175.949 ANA MARIA DIETRICH STEFFENS | C64: anadietrich.consultora@gmail.com | D64: GABRIELLY VARRICHIO
A65: 210427 | B65: 7LS CORRETORA DE SEGUROS LTDA | C65: corretora7ls@gmail.com | D65: MICHELE OLIVEIRA
A66: 202494 | B66: A 2 C TECHNOLOGY - EIRELI (STENIO) | D66: ALVARO VARELA
A67: 200844 | B67: A A DOS SANTOS CORRETORA DE BENEFICIOS E SEGUROS | C67: TSICORRETORA@GMAIL.COM | D67: AMANDA SOUZA
A68: 216760 | B68: A A F CORRETORA DE SEGUROS LTDA | C68: excelenciaseguros@excelenciasegtrab.com.br | D68: AMANDA SOUZA
A69: 203812 | B69: A C Camara Corretora e ADM Seguros LTDA | C69: antoniocarlos@accamaraseguros.com.br | D69: ALVARO VARELA
A70: 205532 | B70: A DE M FEITOZA - EIRELI | C70: afraniofeitoza@gmail.com | D70: BEIBIANA MARQUES
A71: 200414 | B71: A DE M TAKAKI CORRETORA DE SEGUROS | C71: allan@takakiseguros.com.br | D71: THAYNARA SANTOS
A72: 79033 | B72: A DE SOUZA CORRETAGEM DE SEGUROS | C72: andrecorretordeseguros@hotmail.com | D72: THAYNARA SANTOS
A73: 216372 | B73: A FRESTA SOLUCOES FINANCEIRAS LTDA | C73: annafrestaseguros@gmail.com | D73: CINTIANY ROCHA
A74: 183352 | B74: A G CONSULTORIA EM SEGUROS E PLANOS DE SAUDE | C74: contato@consultag.com.br | D74: ALVARO VARELA
A75: 51878 | B75: A G GARROUX CORRETAGEM DE SEGUROS ME | C75: ag.garroux@gmail.com | D75: BEIBIANA MARQUES
A76: 202443 | B76: A L B ADMINISTRADORA E CORRETORA DE SEGUROS EIRELI | C76: comercial@albseguros.com | D76: NATHALIA NARDELLI
A77: 209959 | B77: A REDE NOVA CORPORATION SUADE LTDA | C77: financeiro@aredecorretora.com.br | D77: FLAVIO TEODORO
A78: 106941 | B78: A ROQUETTI CORRETORA DE SEGUROS DE VIDA LTDA | C78: aroquetti@yahoo.com.br | D78: AMANDA SOUZA
... A82: 212435 | B82: A. ARRAIS CONSULTORIA E CORRETORA DE SEGUROS LTDA | C82: aarraisjr@terra.com.br | D82: THAYNARA SANTOS
A83: 204645 | B83: A. DA SILVA FERREIRA LIMITADA | D83: JESSICA GONZAGA
A84: 208934 | B84: A.L.K.S. CONSULTORIA & CORRETORA DE SEGUROS LTDA. | C84: comercial@alksconsultoria.com.br | D84: JENNIFER OLIVEIRA
A85: 209538 | B85: A.P CORRETORA E CONSULTORA DE SEGUROS LTDA | C85: seuplanosegurocontato@gmail.com | D85: DANIELA BARBOSA
A86: 212680 | B86: A.R. CORRETORA DE SEGUROS E VENDA DE PLANOS DE SAUDE E ODONTOLOGICOS LTDA | C86: financeirounimaissaude@gmail.com | D86: DANIELA BARBOSA
A87: 204597 | B87: A.R.DE ARAUJO | D87: JESSICA GONZAGA
A88: 202573 | B88: A.T.W. ADM E CORRETORA DE SEGUROS S/C LTDA | C88: PAULACMORAES@TERRA.COM.BR | D88: AMANDA PUZISKI
A89: 63304 | B89: A1 CORRETORA ( ROSA / RAFAELA) | C89: rosa@a1corretora.com.br | D89: THAYNARA SANTOS
A90: 207308 | B90: A2 INTEGRA CORRETORA DE SEGUROS LTDA | C90: a2integraseguros@gmail.com | D90: JENNIFER OLIVEIRA
A91: 216308 | B91: A3 VALENTE CORRETORA DE SEGUROS LTDA | C91: contato@a3valenteseguros.com.br | D91: SP CARE
A92: 98554 | B92: A6 SERVICOS E CORRET DE SEG EIRELLI | C92: glaucio@a6corretora.com.br | D92: THAYNARA SANTOS
A93: 202244 | B93: AACL | D93: ALVARO VARELA
A94: 216031 | B94: AB CORRETORA DE SEGUROS E SOLUCOES DE RISCO LTDA | C94: bemsegurocorretora@uol.com.br | D94: NATHALIA NARDELLI
A95: 86224 | B95: ABDALA CORRETORA DE SEGUROS | C95: paulianafrisco@yahoo.com.br | D95: AMANDA SOUZA
A96: 202674 | B96: ABET ADMINISTRADORA E CORRETORA DE SEGUROS LTDA | C96: reynaldo.jose@abet.com.br | D96: AMANDA SOUZA
A97: 63305 | B97: ABI AFFINITY - JULIANA RIBEIRO | D97: ALVARO VARELA
A98: 51781 | B98: ABI CONSULTORIA | C98: varelacorseg@uol.com.br | D98: ALVARO VARELA
A99: 204041 | B99: Abia de Souza da Silva | C99: marcio@saudeseguros.net.br | D99: GABRIELLY VARRICHIO
A100: 211441 | B100: Abigail Chaves Soares e Sousa | D100: LAIS LIMA
A101: 51500 | B101: ABIMAEL NEVES DA SILVA | D101: ALVARO VARELA
A102: 115410 | B102: ABIMAIR ALVES DOS SANTOS | C102: asmbia@gmail.com | D102: NATHALIA NARDELLI
A103: 135923 | B103: ABM CORRETORA DE SEGUROS LTDA | D103: GABRIELLY VARRICHIO
A104: 212050 | B104: ABN BRASIL CORRETORA DE SEGUROS LTDA | C104: a.barbosaneto@abnbrasil.seg.br | D104: BRUNA SANTANA
A105: 204568 | B105: Abner Ferreira Gonçalves | C105: abnerferreiranovo@gmail.com | D105: VINICIUS ADDEU SUP
A106: 107976 | B106: ABOUT CORRETORA DE SEGUROS LTDA | C106: luana.humana@hotmail.com | D106: JESSICA GONZAGA
A107: 207615 | B107: Abr e Siq Corretora de Seguros Ltda | C107: priscila@abreuseguros.com | D107: AMANDA SOUZA
A108: 92384 | B108: ABRACE ADM E CORRET DE SEG LTDA ME | C108: abrace@abraceseguros.com.br | D108: THALITA MELO
A109: 66469 | B109: ABRACK CORRETORA DE SEGUROS E GESTAO BENEFICIOS | C109: karinagomes@abrackseguros.com.br | D109: AMANDA SOUZA
A110: 213424 | B110: ABSOLUT LIFE PLANOS DE SAUDE | D110: INGRID SOUZA
A111: 216778 | B111: ABSOLUTA CORRETORA E ADMINISTRADORA DE SEGUROS LTDA | C111: lilian@corretoraabsoluta.com.br | D111: GABRIELLY VARRICHIO
A112: 203513 | B112: AC ASSIS FERNANDES CORRETORA DE SEGUROS LTDA | D112: MATHIAS SILVA
A113: 216083 | B113: ACCEND BROKERS LTDA | C113: vendas@accendbrokers.com | D113: THALITA MELO
...
